.coveragerc
CHANGES.rst
MANIFEST.in
README.rst
setup.cfg
setup.py
tox.ini
tests/test_secret.py
websauna/__init__.py
websauna.j2secret.egg-info/PKG-INFO
websauna.j2secret.egg-info/SOURCES.txt
websauna.j2secret.egg-info/dependency_links.txt
websauna.j2secret.egg-info/not-zip-safe
websauna.j2secret.egg-info/requires.txt
websauna.j2secret.egg-info/top_level.txt
websauna/j2secret/__init__.py