Metadata-Version: 1.1
Name: websauna.j2secret
Version: 1.0.0a1
Summary: Websauna Jinja2 extension that adds a tag to generate secrets.
Home-page: https://github.com/websauna/websauna.j2secret
Author: Websauna Team
Author-email: developers@websauna.org
License: MIT
Keywords: jinja2,websauna,pyramid
Platform: UNKNOWN
Classifier: Development Status :: 3 - Alpha
Classifier: Environment :: Console
Classifier: Intended Audience :: Developers
Classifier: Natural Language :: English
Classifier: License :: OSI Approved :: BSD License
Classifier: Programming Language :: Python
Classifier: Programming Language :: Python :: 3
Classifier: Programming Language :: Python :: 3.4
Classifier: Programming Language :: Python :: 3.5
Classifier: Programming Language :: Python :: 3.6
Classifier: Programming Language :: Python :: Implementation :: CPython
Classifier: Topic :: Software Development
